{
  "version": "0.1.0",
  "database": {
    "dbVersion": "0.1.0",
    "dbType": "PostgreSQL",
    "dbHost": "",
    "dbPort": 54321,
    "dbName": "",
    "dbUser": "",
    "dbPassword": "",
    "ssl": {
      "rejectUnauthorized": false,
      "ca": "",
      "key": "",
      "cert": ""
    }
  },
  "api": {
    "url": "http://localhost",
    "host": "",
    "port": 8080,
    "debugging": false,
    "uploadPath": "data",
    "secret": "",
    "passwordSalt": "",
    "shibboleth": {
      "secret": "",
      "windowURL": ""
    }
  }
}
